cricketstats/__init__.py
cricketstats/cricketstats.py
cricketstats/mpmatchsim.py
cricketstats/playerindex.json
cricketstats/playerindexing.py
cricketstats/playersim.py
cricketstats/statsprocessor.py
cricketstats-0.1.8.dist-info/METADATA
cricketstats-0.1.8.dist-info/WHEEL
cricketstats-0.1.8.dist-info/licenses/LICENSE
cricketstats-0.1.8.dist-info/RECORD
