Metadata-Version: 2.4
Name: cricketstats
Version: 0.1.8
Summary: A cricket analytics package for cricsheet data
Project-URL: Homepage, https://github.com/nsaranga/cricketstats/
Project-URL: Bug Tracker, https://github.com/nsaranga/cricketstats/issues
Author-email: Saranga Sudarshan <nsaranga@hotmail.com>
License:                     GNU GENERAL PUBLIC LICENSE
License-File: LICENSE
Classifier: License :: OSI Approved :: GNU General Public License v3 (GPLv3)
Classifier: Operating System :: OS Independent
Classifier: Programming Language :: Python :: 3
Requires-Python: >=3.7
